unfolding_linear/__init__.py
unfolding_linear/methods.py
unfolding_linear/train_methods.py
unfolding_linear/utils.py
unfolding_linear-0.1.0.dist-info/LICENSE
unfolding_linear-0.1.0.dist-info/METADATA
unfolding_linear-0.1.0.dist-info/WHEEL
unfolding_linear-0.1.0.dist-info/top_level.txt
unfolding_linear-0.1.0.dist-info/RECORD
