Metadata-Version: 2.1
Name: unfolding-linear
Version: 0.1.0
Summary: Deep unfolding of iterative methods to solve linear equations
Home-page: https://github.com/Salahberra2022/deep_unfolding
Author: Salah Berra
Author-email: salahberra39@gmail.com
License: GPLv3
Classifier: Development Status :: 3 - Alpha
Classifier: Intended Audience :: Science/Research
Classifier: Intended Audience :: Education
Classifier: License :: OSI Approved :: GNU General Public License v3 (GPLv3)
Classifier: Programming Language :: Python :: 3
License-File: LICENSE
Requires-Dist: numpy (>=1.20.0)
Requires-Dist: torch (>=2.2.0)
